[
    {
      "Username": "Jim",
      "Gender": "male",
      "DateOfBirth": "1995-09-19",
      "Password": "password",
      "Created": "2017-04-08",
      "LastActive": "2017-04-08",
      "Photos": [
        {
          "url": "https://randomuser.me/api/portraits/men/14.jpg",
          "isMain": true,
          "description": "Occaecat cillum mollit sint minim in ad cupidatat aliqua eu sint incididunt."
        }
      ]
    },
    {
      "Username": "Mccormick",
      "Gender": "male",
      "DateOfBirth": "1984-08-15",
      "Password": "password",
      "Created": "2017-01-23",
      "LastActive": "2017-01-23",
      "Photos": [
        {
          "url": "https://randomuser.me/api/portraits/women/29.jpg",
          "isMain": true,
          "description": "Est tempor incididunt ipsum aliquip sit et occaecat excepteur."
        }
      ]
    },
    {
      "Username": "Shaffer",
      "Gender": "male",
      "DateOfBirth": "1964-05-25",
      "Password": "password",
      "Created": "2017-03-21",
      "LastActive": "2017-03-21",
      "Photos": [
        {
          "url": "https://randomuser.me/api/portraits/women/25.jpg",
          "isMain": true,
          "description": "Ea fugiat voluptate pariatur laborum exercitation."
        }
      ]
    },
    {
      "Username": "Wilkins",
      "Gender": "male",
      "DateOfBirth": "1964-03-25",
      "Password": "password",
      "Created": "2017-02-28",
      "LastActive": "2017-02-28",
      "Photos": [
        {
          "url": "https://randomuser.me/api/portraits/women/85.jpg",
          "isMain": true,
          "description": "Velit ipsum ea fugiat est voluptate aute laborum sit."
        }
      ]
    },
    {
      "Username": "Oliver",
      "Gender": "male",
      "DateOfBirth": "1964-04-23",
      "Password": "password",
      "Created": "2017-05-12",
      "LastActive": "2017-05-12",
      "Photos": [
        {
          "url": "https://randomuser.me/api/portraits/women/4.jpg",
          "isMain": true,
          "description": "Pariatur eiusmod aute proident pariatur."
        }
      ]
    }
  ]